command_based_framework/__init__.py
command_based_framework/_common.py
command_based_framework/actions.py
command_based_framework/commands.py
command_based_framework/exceptions.py
command_based_framework/robot.py
command_based_framework/scheduler.py
command_based_framework/subsystems.py
command_based_framework-1.3.0.dist-info/LICENSE.txt
command_based_framework-1.3.0.dist-info/METADATA
command_based_framework-1.3.0.dist-info/WHEEL
command_based_framework-1.3.0.dist-info/top_level.txt
command_based_framework-1.3.0.dist-info/RECORD
