Metadata-Version: 2.1
Name: command-based-framework
Version: 1.3.0
Summary: Underlying control system for GRR's robotics systems.
Home-page: https://github.com/Great-River-Robotics/command-based-framework
Author: Great River Robotics
Author-email: 
License: MIT
Project-URL: Documentation, https://pyscaffold.org/
Platform: any
Classifier: Development Status :: 4 - Beta
Classifier: Programming Language :: Python
Requires-Python: >=3.7
License-File: LICENSE.txt
Requires-Dist: typing-extensions ; python_version < "3.10"
Requires-Dist: importlib-metadata ; python_version < "3.8"
Provides-Extra: testing
Requires-Dist: setuptools ; extra == 'testing'
Requires-Dist: pytest ; extra == 'testing'
Requires-Dist: mock ; extra == 'testing'
Requires-Dist: coverage ; extra == 'testing'
Requires-Dist: typing-extensions ; extra == 'testing'
